{
  "notas": [
    {
      "id": 1,
      "titulo": "Nota 1",
      "texto": "Qualquer coisa aqui, só para preencher espaço"
    },
    {
      "id": 2,
      "titulo": "Nota 2",
      "texto": "Qualquer coisa aqui, só para preencher espaço"
    },
    {
      "titulo": "asdsad",
      "texto": "asdasdasd",
      "id": 3
    },
    {
      "titulo": "Minha nota",
      "texto": "mskladklasdas",
      "id": 4
    },
    {
      "titulo": "klasjkdlajdkl",
      "texto": "kslajdklasjdkasd",
      "id": 5
    },
    {
      "titulo": "klasjkdlajdkl",
      "texto": "kslajdklasjdkasd",
      "id": 6
    },
    {
      "titulo": "notinha",
      "texto": "sajkdhjkashd",
      "id": 7
    },
    {
      "titulo": "Minha nota 56",
      "texto": "shdjskhadjksdhjaskdhajk",
      "id": 8
    },
    {
      "id": 9,
      "titulo": "oloco",
      "texto": "hkjsakdljsakld\n"
    }
  ]
}